libdct/__init__.py
libdct/feature.py
libdct-0.0.3.dist-info/METADATA
libdct-0.0.3.dist-info/WHEEL
libdct-0.0.3.dist-info/top_level.txt
libdct-0.0.3.dist-info/RECORD
