Metadata-Version: 2.1
Name: libdct
Version: 0.0.3
Summary: A library for audio processing by Discrete Cosine Transform (DCT) 
Home-page: https://github.com/ranchlai/libdct
Author: Lai Yongquan
Author-email: ranchlai@163.com
License: UNKNOWN
Platform: UNKNOWN
Classifier: Programming Language :: Python :: 3
Classifier: License :: OSI Approved :: MIT License
Classifier: Operating System :: OS Independent
Requires-Python: >=3.6
